{
	"info": {
		"_postman_id": "d098f868-a285-40b5-8bbc-98612c588696",
		"name": "curso-spring-ionic",
		"schema": "https://schema.getpostman.com/json/collection/v2.1.0/collection.json"
	},
	"item": [
		{
			"name": "Consultar todas as categorias",
			"request": {
				"method": "GET",
				"header": [],
				"url": {
					"raw": "{{host}}/categorias",
					"host": [
						"{{host}}"
					],
					"path": [
						"categorias"
					]
				}
			},
			"response": []
		},
		{
			"name": "Consultar categorias por id",
			"request": {
				"method": "GET",
				"header": [],
				"url": {
					"raw": "{{host}}/categorias/1",
					"host": [
						"{{host}}"
					],
					"path": [
						"categorias",
						"1"
					]
				}
			},
			"response": []
		},
		{
			"name": "Consultar clientes por id",
			"request": {
				"method": "GET",
				"header": [
					{
						"key": "Authorization",
						"value": "Bearer eyJhbGciOiJIUzUxMiJ9.eyJzdWIiOiJkaWVnb2xwMS5kZXZlbG9wbWVudEBnbWFpbC5jb20iLCJleHAiOjE1ODYzNTQ4OTh9.qIRh-RpauysTtn0fHvNMuNkgmQhedoEfAoMHw7AMKF54hQIp-nnTQTvsceht1uYLvN8VVD37dfx6J5cUMQz9Wg",
						"type": "text"
					}
				],
				"url": {
					"raw": "{{host}}/clientes/2",
					"host": [
						"{{host}}"
					],
					"path": [
						"clientes",
						"2"
					]
				}
			},
			"response": []
		},
		{
			"name": "Consultar pedidos por id",
			"request": {
				"method": "GET",
				"header": [
					{
						"key": "Authorization",
						"value": "Bearer eyJhbGciOiJIUzUxMiJ9.eyJzdWIiOiJkaWVnb2xwLmRldmVsb3BtZW50QGdtYWlsLmNvbSIsImV4cCI6MTU4NjM1MTE5NX0.u_Ow6yQfwUdNl1gXaTYnyNxCDJ2A13D365bQLVp3yiUmSVdHQ2Oy6HVwzeetKBGyNTNcHkuj3qMOI6xeswHENQ",
						"type": "text"
					}
				],
				"url": {
					"raw": "{{host}}/pedidos/1",
					"host": [
						"{{host}}"
					],
					"path": [
						"pedidos",
						"1"
					]
				}
			},
			"response": []
		},
		{
			"name": "Deletar categoria por id",
			"request": {
				"method": "DELETE",
				"header": [],
				"body": {
					"mode": "formdata",
					"formdata": []
				},
				"url": {
					"raw": "{{host}}/categorias/8",
					"host": [
						"{{host}}"
					],
					"path": [
						"categorias",
						"8"
					]
				}
			},
			"response": []
		},
		{
			"name": "Deletarcliente por id",
			"request": {
				"method": "DELETE",
				"header": [],
				"body": {
					"mode": "formdata",
					"formdata": []
				},
				"url": {
					"raw": "{{host}}/clientes/2",
					"host": [
						"{{host}}"
					],
					"path": [
						"clientes",
						"2"
					]
				}
			},
			"response": []
		},
		{
			"name": "Consultar categorias paginadas",
			"request": {
				"method": "GET",
				"header": [],
				"url": {
					"raw": "{{host}}/categorias/page?page=0&linesPerPage=&orderBy=&direction=DESC",
					"host": [
						"{{host}}"
					],
					"path": [
						"categorias",
						"page"
					],
					"query": [
						{
							"key": "page",
							"value": "0"
						},
						{
							"key": "linesPerPage",
							"value": ""
						},
						{
							"key": "orderBy",
							"value": ""
						},
						{
							"key": "direction",
							"value": "DESC"
						}
					]
				}
			},
			"response": []
		},
		{
			"name": "Criar categoria",
			"request": {
				"method": "POST",
				"header": [
					{
						"key": "Content-Type",
						"value": "application/json"
					},
					{
						"key": "Authorization",
						"value": "Bearer eyJhbGciOiJIUzUxMiJ9.eyJzdWIiOiJkaWVnb2xwMS5kZXZlbG9wbWVudEBnbWFpbC5jb20iLCJleHAiOjE1ODYzNTIxNDh9.I-MY3x9ZumWgosm9xaP_AlO4tu9dro-OxH9KWwwwwmOCTqWLyVtMyZwSoRp-qlDakaf41IbrBMdwD6UdKurM3g",
						"type": "text"
					}
				],
				"body": {
					"mode": "raw",
					"raw": "{\n  \"nome\": \"Infantil\"\n}"
				},
				"url": {
					"raw": "{{host}}/categorias",
					"host": [
						"{{host}}"
					],
					"path": [
						"categorias"
					]
				}
			},
			"response": []
		},
		{
			"name": "Atualizar categorias",
			"request": {
				"method": "PUT",
				"header": [
					{
						"key": "Content-Type",
						"value": "application/json"
					}
				],
				"body": {
					"mode": "raw",
					"raw": "{\n  \"nome\": \"Ferramentas\"\n}"
				},
				"url": {
					"raw": "{{host}}/categorias/9",
					"host": [
						"{{host}}"
					],
					"path": [
						"categorias",
						"9"
					]
				}
			},
			"response": []
		},
		{
			"name": "Consultar clientes",
			"request": {
				"method": "GET",
				"header": [],
				"url": {
					"raw": "{{host}}/clientes",
					"host": [
						"{{host}}"
					],
					"path": [
						"clientes"
					]
				}
			},
			"response": []
		},
		{
			"name": "Consultar clientes paginada",
			"request": {
				"method": "GET",
				"header": [],
				"url": {
					"raw": "{{host}}/clientes/page",
					"host": [
						"{{host}}"
					],
					"path": [
						"clientes",
						"page"
					]
				}
			},
			"response": []
		},
		{
			"name": "Atualizar cliente por id",
			"request": {
				"method": "PUT",
				"header": [],
				"body": {
					"mode": "raw",
					"raw": "{\n\t\"nome\": \"Maria Pereira\",\n    \"email\": \"maria@gmail.com\"\n}",
					"options": {
						"raw": {
							"language": "json"
						}
					}
				},
				"url": {
					"raw": "{{host}}/clientes/1",
					"host": [
						"{{host}}"
					],
					"path": [
						"clientes",
						"1"
					]
				}
			},
			"response": []
		},
		{
			"name": "Criar cliente",
			"request": {
				"method": "POST",
				"header": [],
				"body": {
					"mode": "raw",
					"raw": "{\n\t\"nome\": \"Maria Pereira\",\n    \"email\": \"maria@gmail.com\",\n    \"cpfOuCnpj\": \"52740225709\",\n    \"tipo\": 1,\n    \"telefone1\": \"(41) 98899-7854\",\n    \"telefone2\": \"(41) 98899-3434\",\n    \"logradouro\":\"Rua Tevez\",\n\t\"numero\":900,\n\t\"complemento\": \"Apto 401\",\n\t\"bairro\":\"Centro Civico\",\n\t\"cep\":\"81670-020\",\n\t\"cidadeId\":1\n\n}",
					"options": {
						"raw": {
							"language": "json"
						}
					}
				},
				"url": {
					"raw": "{{host}}/clientes",
					"host": [
						"{{host}}"
					],
					"path": [
						"clientes"
					]
				}
			},
			"response": []
		},
		{
			"name": "Pesquisa de produtos",
			"request": {
				"method": "GET",
				"header": [],
				"url": {
					"raw": "{{host}}/produtos?nome=or&categorias=1",
					"host": [
						"{{host}}"
					],
					"path": [
						"produtos"
					],
					"query": [
						{
							"key": "nome",
							"value": "or"
						},
						{
							"key": "categorias",
							"value": "1"
						}
					]
				}
			},
			"response": []
		},
		{
			"name": "Criar um pedido",
			"request": {
				"method": "POST",
				"header": [
					{
						"key": "Authorization",
						"value": "Bearer eyJhbGciOiJIUzUxMiJ9.eyJzdWIiOiJkaWVnb2xwMS5kZXZlbG9wbWVudEBnbWFpbC5jb20iLCJleHAiOjE1ODYzNTY1NzZ9.ZITc3XWJmTUiCk1On_R6yAAhqBAP_QGq6Pf86XXZTHn6SvOCjkZhyFdHqF6c1ASfGFXMrmiBrjQjWMoPlFGAcg",
						"type": "text"
					}
				],
				"body": {
					"mode": "raw",
					"raw": "{\n\t\"cliente\" : {\"id\" : 1},\n\t\"enderecoDeEntrega\" : {\"id\" : 1},\n\t\"pagamento\" : {\n\t\t\"numeroDeParcelas\" : 10,\n\t\t\"@type\": \"pagamentoComCartao\"\n\t},\n\t\"itens\" : \n\t[\n\t\t{\n\t\t\t\"quantidade\" : 2,\n\t\t\t\"produto\" : {\"id\" : 3}\n\t\t},\n\t\t{\n\t\t\t\"quantidade\" : 1,\n\t\t\t\"produto\" : {\"id\" : 1}\n\t\t}\n\t]\n}",
					"options": {
						"raw": {
							"language": "json"
						}
					}
				},
				"url": {
					"raw": "{{host}}/pedidos",
					"host": [
						"{{host}}"
					],
					"path": [
						"pedidos"
					]
				}
			},
			"response": []
		},
		{
			"name": "Consultar pedido por id",
			"request": {
				"method": "GET",
				"header": [],
				"url": {
					"raw": "{{host}}/pedidos/1",
					"host": [
						"{{host}}"
					],
					"path": [
						"pedidos",
						"1"
					]
				}
			},
			"response": []
		},
		{
			"name": "Login cliente",
			"request": {
				"method": "POST",
				"header": [],
				"body": {
					"mode": "raw",
					"raw": "{\n\t\"email\": \"diegolp1.development@gmail.com\",\n\t\"senha\": \"123\"\n}",
					"options": {
						"raw": {
							"language": "json"
						}
					}
				},
				"url": {
					"raw": "{{host}}/login",
					"host": [
						"{{host}}"
					],
					"path": [
						"login"
					]
				}
			},
			"response": []
		},
		{
			"name": "Refresh token",
			"request": {
				"method": "POST",
				"header": [
					{
						"key": "Authorization",
						"value": "Bearer eyJhbGciOiJIUzUxMiJ9.eyJzdWIiOiJkaWVnb2xwMS5kZXZlbG9wbWVudEBnbWFpbC5jb20iLCJleHAiOjE1ODYzNjA3NzN9.nT9QUeEVD64i0BSPQr-lKWjlfY7ZJFfr757o3Y4piaGER-vVOU12aKeTVkOawqJuqZAo9G-Hy8XP-Nukep7now",
						"type": "text"
					}
				],
				"url": {
					"raw": "{{host}}/auth/refresh-token",
					"host": [
						"{{host}}"
					],
					"path": [
						"auth",
						"refresh-token"
					]
				}
			},
			"response": []
		},
		{
			"name": "Recuperando senha de usuário",
			"request": {
				"method": "POST",
				"header": [],
				"body": {
					"mode": "raw",
					"raw": "{\n\t\"email\": \"diegolp.development@gmail.com\"\n}",
					"options": {
						"raw": {
							"language": "json"
						}
					}
				},
				"url": {
					"raw": "{{host}}/auth/forgot",
					"host": [
						"{{host}}"
					],
					"path": [
						"auth",
						"forgot"
					]
				}
			},
			"response": []
		},
		{
			"name": "Salvar imagem de perfil  para clientes",
			"request": {
				"method": "POST",
				"header": [],
				"body": {
					"mode": "formdata",
					"formdata": [
						{
							"key": "file",
							"type": "file",
							"src": "/home/lemospadilha/Downloads/avatar-2027366_1280.png"
						}
					]
				},
				"url": {
					"raw": "{{host}}/clientes/picture",
					"host": [
						"{{host}}"
					],
					"path": [
						"clientes",
						"picture"
					]
				}
			},
			"response": []
		}
	],
	"protocolProfileBehavior": {}
}